{
  "options": {
    "summaryTrendStats": [
      "avg",
      "min",
      "med",
      "max",
      "p(90)",
      "p(95)"
    ],
    "summaryTimeUnit": "",
    "noColor": false
  },
  "state": {
    "isStdOutTTY": false,
    "isStdErrTTY": false,
    "testRunDurationMs": 60441.629408
  },
  "metrics": {
    "iterations": {
      "values": {
        "count": 2505,
        "rate": 41.444944892045555
      },
      "type": "counter",
      "contains": "default"
    },
    "vus_max": {
      "type": "gauge",
      "contains": "default",
      "values": {
        "value": 12,
        "min": 12,
        "max": 12
      }
    },
    "data_sent": {
      "type": "counter",
      "contains": "data",
      "values": {
        "rate": 16126.335599268099,
        "count": 974702
      }
    },
    "http_req_sending": {
      "values": {
        "p(90)": 0.06358599999999996,
        "p(95)": 0.09168,
        "avg": 0.06054214820717125,
        "min": 0.00787,
        "med": 0.02956,
        "max": 16.981201
      },
      "type": "trend",
      "contains": "time"
    },
    "rate_under_3s": {
      "contains": "default",
      "values": {
        "rate": 1,
        "passes": 2505,
        "fails": 0
      },
      "type": "rate"
    },
    "http_req_failed": {
      "thresholds": {
        "rate<0.01": {
          "ok": true
        }
      },
      "type": "rate",
      "contains": "default",
      "values": {
        "rate": 0.0007968127490039841,
        "passes": 2,
        "fails": 2508
      }
    },
    "http_req_receiving": {
      "type": "trend",
      "contains": "time",
      "values": {
        "med": 5.8165675,
        "max": 377.049874,
        "p(90)": 164.31021349999997,
        "p(95)": 199.89095135,
        "avg": 48.299978880876516,
        "min": 0.03721
      }
    },
    "http_req_blocked": {
      "type": "trend",
      "contains": "time",
      "values": {
        "avg": 0.015259578884462135,
        "min": 0.00272,
        "med": 0.00664,
        "max": 1.266732,
        "p(90)": 0.010171,
        "p(95)": 0.016099949999999977
      }
    },
    "iteration_duration": {
      "type": "trend",
      "contains": "time",
      "values": {
        "avg": 288.1274796127744,
        "min": 108.077747,
        "med": 276.105545,
        "max": 883.842806,
        "p(90)": 492.87804159999996,
        "p(95)": 554.4083558
      }
    },
    "http_req_waiting": {
      "type": "trend",
      "contains": "time",
      "values": {
        "med": 151.327272,
        "max": 640.785125,
        "p(90)": 276.6748821,
        "p(95)": 323.82929819999987,
        "avg": 138.27947486812772,
        "min": 2.480853
      }
    },
    "data_received": {
      "type": "counter",
      "contains": "data",
      "values": {
        "count": 6355586279,
        "rate": 105152464.30730374
      }
    },
    "http_req_connecting": {
      "type": "trend",
      "contains": "time",
      "values": {
        "p(95)": 0,
        "avg": 0.0048195247011952195,
        "min": 0,
        "med": 0,
        "max": 1.217062,
        "p(90)": 0
      }
    },
    "checks": {
      "contains": "default",
      "values": {
        "passes": 2505,
        "fails": 0,
        "rate": 1
      },
      "type": "rate"
    },
    "group_duration": {
      "type": "trend",
      "contains": "time",
      "values": {
        "avg": 187.26752168023967,
        "min": 7.743052,
        "med": 174.534918,
        "max": 783.65591,
        "p(90)": 392.19312299999996,
        "p(95)": 453.86540639999976
      }
    },
    "http_req_duration": {
      "values": {
        "max": 782.551019,
        "p(90)": 391.85795559999997,
        "p(95)": 453.3074430499998,
        "avg": 186.63999589721155,
        "min": 2.609144,
        "med": 173.842439
      },
      "type": "trend",
      "contains": "time"
    },
    "http_reqs": {
      "type": "counter",
      "contains": "default",
      "values": {
        "count": 2510,
        "rate": 41.527669332947845
      }
    },
    "vus": {
      "values": {
        "value": 12,
        "min": 12,
        "max": 12
      },
      "type": "gauge",
      "contains": "default"
    },
    "rate_under_1s": {
      "type": "rate",
      "contains": "default",
      "values": {
        "rate": 1,
        "passes": 2505,
        "fails": 0
      }
    },
    "http_req_duration{expected_response:true}": {
      "type": "trend",
      "contains": "time",
      "values": {
        "p(90)": 391.8626348,
        "p(95)": 453.3982021500001,
        "avg": 186.78537470893178,
        "min": 3.243304,
        "med": 174.1145415,
        "max": 782.551019
      }
    },
    "http_req_tls_handshaking": {
      "type": "trend",
      "contains": "time",
      "values": {
        "p(90)": 0,
        "p(95)": 0,
        "avg": 0,
        "min": 0,
        "med": 0,
        "max": 0
      }
    },
    "rate_under_2s": {
      "type": "rate",
      "contains": "default",
      "values": {
        "rate": 1,
        "passes": 2505,
        "fails": 0
      }
    }
  },
  "setup_data": {
    "employeeId": 1,
    "serviceId": 1,
    "token": "eyJhbGciOiJIUzI1NiJ9.eyJyb2xlIjoiU1lTQURNSU4iLCJ1c2VySWQiOjIsInN1YiI6InN5c2FkbWluQHNhbGFvLmNvbSIsImlhdCI6MTc4MzE5NzIyOCwiZXhwIjoxNzgzMTk4MTI4fQ.CzDReR0-ckDkEPOc9Z3PUJRxs41Y4y3YHYv3H2LeJag"
  },
  "root_group": {
    "id": "d41d8cd98f00b204e9800998ecf8427e",
    "groups": [
      {
        "path": "::POST Manual CashFlow Entry",
        "id": "0ffb40edbe0d126502832ebd0ea10727",
        "groups": [],
        "checks": [
            {
              "passes": 496,
              "fails": 0,
              "name": "status 201 - CashFlow Entry Created",
              "path": "::POST Manual CashFlow Entry::status 201 - CashFlow Entry Created",
              "id": "2903677dbd913eb4a7a178d3574d59d9"
            }
          ],
        "name": "POST Manual CashFlow Entry"
      },
      {
        "id": "26debf75e3100b82dea0f380bd3f15f5",
        "groups": [],
        "checks": [
            {
              "name": "status 201 - Create Appointment",
              "path": "::POST Create Appointment Request::status 201 - Create Appointment",
              "id": "de6dcad74d6a853f813a8e5c4a331b4a",
              "passes": 508,
              "fails": 0
            }
          ],
        "name": "POST Create Appointment Request",
        "path": "::POST Create Appointment Request"
      },
      {
        "name": "GET Financial Report",
        "path": "::GET Financial Report",
        "id": "7e4e748679095df65aa9e120102710e4",
        "groups": [],
        "checks": [
            {
              "fails": 0,
              "name": "status 200 - Financial Report",
              "path": "::GET Financial Report::status 200 - Financial Report",
              "id": "487cd77236b9aeb60da8f72fc597bdbf",
              "passes": 766
            }
          ]
      },
      {
        "name": "GET All Appointments",
        "path": "::GET All Appointments",
        "id": "2039228a6173132fa6e7fc29e0d7cfe9",
        "groups": [],
        "checks": [
            {
              "name": "status 200 - List Appointments",
              "path": "::GET All Appointments::status 200 - List Appointments",
              "id": "8baabba5880bdd57b135935b977ced67",
              "passes": 735,
              "fails": 0
            }
          ]
      }
    ],
    "checks": [],
    "name": "",
    "path": ""
  }
}